LICENSE
MANIFEST.in
setup.py
starlette_utils/__init__.py
starlette_utils/version.py
starlette_utils.egg-info/PKG-INFO
starlette_utils.egg-info/SOURCES.txt
starlette_utils.egg-info/dependency_links.txt
starlette_utils.egg-info/entry_points.txt
starlette_utils.egg-info/requires.txt
starlette_utils.egg-info/top_level.txt
starlette_utils/backends/__init__.py
starlette_utils/backends/auth_backends.py
starlette_utils/cli/__init__.py
starlette_utils/cli/app.py
starlette_utils/cli/cli.py
starlette_utils/cli/db.py
starlette_utils/cli/project.py
starlette_utils/exception/__init__.py
starlette_utils/exception/exceptions.py
starlette_utils/exception/http_exception.py
starlette_utils/exception/not_found.py
starlette_utils/exception/server_error.py
starlette_utils/middleware/__init__.py
starlette_utils/middleware/auth_middleware.py
starlette_utils/middleware/request_id_middleware.py
starlette_utils/models/__init__.py
starlette_utils/models/base.py
starlette_utils/response/__init__.py
starlette_utils/response/api_endpoints.py
starlette_utils/response/base_endpoints.py
starlette_utils/response/responseViewMixin.py
starlette_utils/response/response_results.py
starlette_utils/schemas/__init__.py
starlette_utils/schemas/schema.py
starlette_utils/schemas/schema_settings.py
starlette_utils/schemas/schemas.py
starlette_utils/schemas/views.py
starlette_utils/schemas/statics/vue3.js
starlette_utils/schemas/statics/css/style.css
starlette_utils/schemas/statics/js/cookie_utils.js
starlette_utils/schemas/statics/js/index.js
starlette_utils/schemas/statics/js/test.js
starlette_utils/schemas/statics/swagger/favicon-16x16.png
starlette_utils/schemas/statics/swagger/favicon-32x32.png
starlette_utils/schemas/statics/swagger/index.html
starlette_utils/schemas/statics/swagger/oauth2-redirect.html
starlette_utils/schemas/statics/swagger/swagger-ui-bundle.js
starlette_utils/schemas/statics/swagger/swagger-ui-bundle.js.map
starlette_utils/schemas/statics/swagger/swagger-ui-es-bundle-core.js
starlette_utils/schemas/statics/swagger/swagger-ui-es-bundle-core.js.map
starlette_utils/schemas/statics/swagger/swagger-ui-es-bundle.js
starlette_utils/schemas/statics/swagger/swagger-ui-es-bundle.js.map
