Metadata-Version: 2.1
Name: starlette-utils
Version: 0.0.14
Summary: starlette Tools.
Home-page: https://gitee.com/hubertshelley/starlette_utils
Author: Hubert Shelley
Author-email: hubertshelley@163.com
License: Apache Software License
Platform: UNKNOWN
Classifier: License :: OSI Approved :: Apache Software License
Classifier: Programming Language :: Python
Classifier: Programming Language :: Python :: 3
Classifier: Programming Language :: Python :: 3.7
Classifier: Programming Language :: Python :: Implementation :: CPython
Classifier: Programming Language :: Python :: Implementation :: PyPy
Requires-Python: >=3.7.0
License-File: LICENSE
